nd4j/__init__.py
nd4j-0.0.0.dist-info/METADATA
nd4j-0.0.0.dist-info/WHEEL
nd4j-0.0.0.dist-info/top_level.txt
nd4j-0.0.0.dist-info/RECORD
